README.rst
setup.py
MUGAlyser.egg-info/PKG-INFO
MUGAlyser.egg-info/SOURCES.txt
MUGAlyser.egg-info/dependency_links.txt
MUGAlyser.egg-info/requires.txt
MUGAlyser.egg-info/top_level.txt
bin/getstats.sh
bin/makeapikeyfile_main.py
bin/meetup_info_main.py
bin/mug_analytics_main.py
bin/mug_db_setup.py
bin/mugalyser_main.py
bin/muginfo_main.py
bin/mugs.sh
bin/pugs.sh
bin/range_query.sh
bin/run_prog.sh
bin/update_atlas.sh
mugalyser/__init__.py
mugalyser/apikey.py
mugalyser/apikey_template.py
mugalyser/attendees.py
mugalyser/audit.py
mugalyser/audit2.py
mugalyser/batchwriter.py
mugalyser/comparedata.py
mugalyser/dotted_dict.py
mugalyser/events.py
mugalyser/feedback.py
mugalyser/gdrive.py
mugalyser/generator_utils.py
mugalyser/getgroups.py
mugalyser/groups.py
mugalyser/meetup_api.py
mugalyser/meetup_writer.py
mugalyser/members.py
mugalyser/mongodb.py
mugalyser/mongodb_argparse.py
mugalyser/mugdata.py
mugalyser/nested_dict.py
mugalyser/upcomingevents.py
mugalyser/version.py
tests/__init__.py
tests/test_MugData.py
tests/test_agg.py
tests/test_attendees.py
tests/test_audit.py
tests/test_batchwriter.py
tests/test_events.py
tests/test_gdrive.py
tests/test_groups.py
tests/test_mains.py
tests/test_meetup_api.py
tests/test_meetup_writer.py
tests/test_members.py
tests/test_parse_uri.py
tests/test_pydrive.py
tests/test_sorter.py
tests/testconnect_main.py
utils/__init__.py
utils/pymongo_shell.py
utils/query.py
utils/singleton.py
webgui/__init__.py
webgui/webgui_main.py