Metadata-Version: 1.1
Name: MUGAlyser
Version: 1.0.6a0
Summary: MUGAlyser - a script to extract data from Meetup into a MongoDB database
Home-page: https://github.com/jdrumgoole/MUGAlyser
Author: Joe Drumgoole
Author-email: joe@joedrumgoole.com
License: AGPL
Keywords: Meetup MUGS MongoDB API
Platform: UNKNOWN
Classifier: Development Status :: 3 - Alpha
Classifier: Intended Audience :: Developers
Classifier: License :: OSI Approved :: GNU Affero General Public License v3
Classifier: Programming Language :: Python :: 2.7
